AUTHORS.rst
CONTRIBUTING.rst
HISTORY.rst
LICENSE
MANIFEST.in
README.rst
setup.cfg
setup.py
docs/Makefile
docs/authors.rst
docs/conf.py
docs/contributing.rst
docs/history.rst
docs/index.rst
docs/installation.rst
docs/make.bat
docs/readme.rst
docs/usage.rst
pysploit/__init__.py
pysploit/pysploit.py
pysploit.egg-info/PKG-INFO
pysploit.egg-info/SOURCES.txt
pysploit.egg-info/dependency_links.txt
pysploit.egg-info/not-zip-safe
pysploit.egg-info/top_level.txt
tests/__init__.py
tests/test_pysploit.py